hentaila/__init__.py
hentaila/__vars__.py
hentaila/hentaila.py
hentaila/simple_utils.py
hentaila/la_types/__init__.py
hentaila/la_types/errors.py
hentaila/la_types/types_la.py
tests_hentaila/__init__.py
tests_hentaila/hentaila_sample.py
hentaila-0.0.2.post0.dist-info/LICENSE
hentaila-0.0.2.post0.dist-info/METADATA
hentaila-0.0.2.post0.dist-info/WHEEL
hentaila-0.0.2.post0.dist-info/top_level.txt
hentaila-0.0.2.post0.dist-info/RECORD
