Metadata-Version: 2.1
Name: hentaila
Version: 0.0.2.post0
Summary: Unofficial https://www3.hentaila.com/ Package
Home-page: https://github.com/TaprisSugarbell/hentaila
Author: SayuOgiwara
Author-email: anonesayu@gmail.com
Project-URL: Issue tracker, https://github.com/TaprisSugarbell/hentaila/issues
License-File: LICENSE
Requires-Dist: beautifulsoup4
Requires-Dist: cloudscraper
